config_resolver/__init__.py
config_resolver/core.py
config_resolver/exc.py
config_resolver/py.typed
config_resolver/util.py
config_resolver/version.txt
config_resolver/handler/__init__.py
config_resolver/handler/base.py
config_resolver/handler/ini.py
config_resolver/handler/json.py
config_resolver-5.1.0.dist-info/LICENSE.txt
config_resolver-5.1.0.dist-info/METADATA
config_resolver-5.1.0.dist-info/WHEEL
config_resolver-5.1.0.dist-info/top_level.txt
config_resolver-5.1.0.dist-info/RECORD
