Metadata-Version: 2.1
Name: config-resolver
Version: 5.1.0
Summary: A small package to automatically find a configuration file.
Home-page: https://github.com/exhuma/config_resolver
Author: Michel Albert
Author-email: michel@albert.lu
License: MIT
Project-URL: Bug Tracker, https://github.com/exhuma/config_resolver/issues
Project-URL: Documentation, https://config-resolver.readthedocs.org/en/latest/
Platform: UNKNOWN
Classifier: Development Status :: 5 - Production/Stable
Classifier: Intended Audience :: Developers
Classifier: License :: OSI Approved :: GNU Lesser General Public License v3 (LGPLv3)
Classifier: Operating System :: POSIX :: Linux
Classifier: Programming Language :: Python
Classifier: Programming Language :: Python :: 3
Classifier: Programming Language :: Python :: 3.6
Classifier: Programming Language :: Python :: 3 :: Only
Classifier: Topic :: Software Development :: Libraries :: Python Modules
Requires-Python: >=3.6
Requires-Dist: packaging
